rundown/__init__.py
rundown/utils/__init__.py
rundown/utils/rundown.py
rundown-0.1.4.dist-info/LICENSE
rundown-0.1.4.dist-info/METADATA
rundown-0.1.4.dist-info/WHEEL
rundown-0.1.4.dist-info/top_level.txt
rundown-0.1.4.dist-info/RECORD
