Metadata-Version: 2.1
Name: rundown
Version: 0.1.4
Summary: Quick and dirty overview of a Pandas DataFrame
Home-page: https://github.com/lucasdurand/rundown
Author: Lucas Durand
Author-email: lucas@lucasdurand.xyz
License: MIT
Platform: UNKNOWN
Classifier: License :: OSI Approved :: MIT License
Classifier: Programming Language :: Python :: 3
Classifier: Programming Language :: Python :: 3.7
Requires-Dist: pandas
Requires-Dist: matplotlib
